iNLP-0.0.2.dist-info/METADATA
iNLP-0.0.2.dist-info/RECORD
iNLP-0.0.2.dist-info/WHEEL
iNLP-0.0.2.dist-info/top_level.txt
inlp/README.md
inlp/__init__.py
inlp/convert/README.md
inlp/convert/__init__.py
inlp/convert/char/__init__.py
inlp/convert/chinese/__init__.py
inlp/convert/chinese/langconv.py
inlp/convert/chinese/zh_wiki.py
inlp/data/__init__.py
inlp/data/chaizi-ft.txt
inlp/data/chaizi-jt.txt
inlp/data/cilin2.txt
inlp/data/hownet.dat
inlp/data/new_cilin.txt
inlp/data/strokes.json
inlp/explode/__init__.py
inlp/explode/strokes/__init__.py
inlp/explode/strokes/character_stoke.py
inlp/explode/strokes/character_stoke_handian.py
inlp/explode/strokes/handian.py
inlp/similarity/__init__.py
inlp/similarity/thesaurus/__init__.py
inlp/utils/__init__.py
